odoo/addons/account_journal_general_sequence/README.rst
odoo/addons/account_journal_general_sequence/__init__.py
odoo/addons/account_journal_general_sequence/__manifest__.py
odoo/addons/account_journal_general_sequence/i18n/account_journal_general_sequence.pot
odoo/addons/account_journal_general_sequence/i18n/es.po
odoo/addons/account_journal_general_sequence/i18n/hr.po
odoo/addons/account_journal_general_sequence/models/__init__.py
odoo/addons/account_journal_general_sequence/models/account_journal.py
odoo/addons/account_journal_general_sequence/models/account_move.py
odoo/addons/account_journal_general_sequence/models/account_move_line.py
odoo/addons/account_journal_general_sequence/readme/CONFIGURE.rst
odoo/addons/account_journal_general_sequence/readme/CONTRIBUTORS.rst
odoo/addons/account_journal_general_sequence/readme/DESCRIPTION.rst
odoo/addons/account_journal_general_sequence/readme/INSTALL.rst
odoo/addons/account_journal_general_sequence/readme/USAGE.rst
odoo/addons/account_journal_general_sequence/security/ir.model.access.csv
odoo/addons/account_journal_general_sequence/static/description/icon.png
odoo/addons/account_journal_general_sequence/static/description/index.html
odoo/addons/account_journal_general_sequence/tests/__init__.py
odoo/addons/account_journal_general_sequence/tests/test_numbering.py
odoo/addons/account_journal_general_sequence/views/account_journal.xml
odoo/addons/account_journal_general_sequence/views/account_move.xml
odoo/addons/account_journal_general_sequence/views/account_move_line.xml
odoo/addons/account_journal_general_sequence/wizards/__init__.py
odoo/addons/account_journal_general_sequence/wizards/account_move_renumber_wizard.py
odoo/addons/account_journal_general_sequence/wizards/account_move_renumber_wizard_views.xml
odoo14_addon_account_journal_general_sequence-14.0.1.1.0.dist-info/METADATA
odoo14_addon_account_journal_general_sequence-14.0.1.1.0.dist-info/WHEEL
odoo14_addon_account_journal_general_sequence-14.0.1.1.0.dist-info/top_level.txt
odoo14_addon_account_journal_general_sequence-14.0.1.1.0.dist-info/RECORD
